src/__init__.py
src/organizer.py
files_organizer-1.0.3.dist-info/LICENSE.md
files_organizer-1.0.3.dist-info/METADATA
files_organizer-1.0.3.dist-info/WHEEL
files_organizer-1.0.3.dist-info/entry_points.txt
files_organizer-1.0.3.dist-info/top_level.txt
files_organizer-1.0.3.dist-info/RECORD
