Metadata-Version: 2.1
Name: files-organizer
Version: 1.0.3
Summary: Move files by date into folders month by month
Home-page: https://github.com/xandao6/files-organizer
Author: Alexandre Calil Martins Fonseca
Author-email: alexandrecalilmf@gmail.com
License: MIT
Download-URL: https://pypi.org/project/files-organizer
Keywords: organizerdate to folders,images organizer,images date to folders
Platform: UNKNOWN
Classifier: Programming Language :: Python :: 3.6
Classifier: Programming Language :: Python :: 3.7
Classifier: Programming Language :: Python :: 3.9
Classifier: Programming Language :: Python :: 3 :: Only
Classifier: Operating System :: OS Independent
Requires-Python: >=3.6
Requires-Dist: fire (>=0.2.1)
Requires-Dist: image
Requires-Dist: pyfiglet (>=0.8)
Provides-Extra: win
Requires-Dist: pywin32 ; extra == 'win'
